vite_transporter/.DS_Store
vite_transporter/__init__.py
vite_transporter/cli.py
vite_transporter/globals.py
vite_transporter/elements/__init__.py
vite_transporter/elements/body_content.py
vite_transporter/elements/link_tag.py
vite_transporter/elements/script_tag.py
vite_transporter/flask/__init__.py
vite_transporter/quart/__init__.py
vite_transporter/utilities/__init__.py
vite_transporter/utilities/compile_vite_apps.py
vite_transporter/utilities/list_vite_apps.py
vite_transporter/utilities/load_vite_app.py
vite_transporter/utilities/print_help.py
vite_transporter/utilities/pyproject_config.py
vite_transporter/utilities/sprinkles.py
vite_transporter-1.1.0.dist-info/entry_points.txt
vite_transporter-1.1.0.dist-info/LICENSE
vite_transporter-1.1.0.dist-info/WHEEL
vite_transporter-1.1.0.dist-info/METADATA
vite_transporter-1.1.0.dist-info/RECORD
