Metadata-Version: 2.1
Name: vite-transporter
Version: 1.1.0
Summary: Transport Vite apps.
Author-email: David Carmichael <david@uilix.com>
Requires-Python: >=3.8
Classifier: Programming Language :: Python :: 3.8
Classifier: Programming Language :: Python :: 3.9
Classifier: Programming Language :: Python :: 3.10
Classifier: Programming Language :: Python :: 3.11
Classifier: Programming Language :: Python :: 3.12
Classifier: Topic :: Internet :: WWW/HTTP :: Dynamic Content
Classifier: Natural Language :: English
Requires-Dist: flask ; extra == "flask"
Requires-Dist: quart ; extra == "quart"
Provides-Extra: flask
Provides-Extra: quart
